globalmart_api2766/__init__.py
globalmart_api2766/api_dealer.py
globalmart_api2766-0.1.dist-info/License.txt
globalmart_api2766-0.1.dist-info/METADATA
globalmart_api2766-0.1.dist-info/WHEEL
globalmart_api2766-0.1.dist-info/top_level.txt
globalmart_api2766-0.1.dist-info/RECORD
